c2048-0.1.0.dist-info/METADATA
c2048-0.1.0.dist-info/WHEEL
c2048-0.1.0.dist-info/licenses/LICENSE
c2048/__init__.py
c2048/__init__.pyi
c2048/py.typed
c2048/c2048.cp312-win_amd64.pyd
c2048-0.1.0.dist-info/RECORD
