Metadata-Version: 2.3
Name: c2048
Version: 0.1.0
Classifier: Programming Language :: Rust
Classifier: Programming Language :: Python :: Implementation :: CPython
Classifier: Programming Language :: Python :: Implementation :: PyPy
License-File: LICENSE
Summary: A Python implementation of the game 2048 written in rust
Keywords: 2048
Author: Carlettos
License: MIT
Requires-Python: >=3.8
Project-URL: Source Code, https://github.com/Carlettos1/c2048
